{
	"policyDetails": {
	  "risks": [
		{
		  "proposer": {
			"person": {
			  "dateOfBirth": "1979-12-31",
			  "dateOfResidency": "1979-12-31",
			  "firstNames": "John D",
			  "gender": "M",
			  "isHomeOwner": false,
			  "isUKResidentFromBirth": true,
			  "lastName": "Jackson",
			  "maritalStatus": "M",
			  "nationality": "U",
			  "numberOfDependentChildren": 0,
			  "title": "003",
			  "isDeceased": false,
			  "personReference": "1212121212"
			},
			"postalAddress": {
			  "addressReference": "GB|RM|A|51314247",
			  "abodeNumber": "Head Office",
			  "UDPRN": "71100571",
			  "addressLine1": "11 Coverham Close",
			  "addressLine2": "addressLine2",
			  "addressLine3": "addressLine3",
			  "buildingName": "Coyote Hall",
			  "buildingNumber": "11",
			  "subBuilding": "Flat 1",
			  "companyName": "ACME Ltd",
			  "constituency": "North Yorkshire",
			  "county": "North Yorkshire",
			  "dataLevel": "Premise",
			  "district": "Hambleton",
			  "poBoxNumber": "1",
			  "label": "11 Coverham Close NORTHALLERTON DL7 8SS UNITED KINGDOM",
			  "postcode": "HX35AX",
			  "street": "Coverham Close",
			  "secondaryStreet": "Castelton Avenue",
			  "townCity": "Northallerton",
			  "buildingType": "Residential"
			},
			"communications": [
			  {
				"method": "Telephone",
				"commsType": "g_mo",
				"details": "07556 123234"
			  }
			],
			"marketingPreferences": [
			  {
				"prefType": "Email",
				"isSelected": false
			  }
			]
		  },
		  "motorRisk": {
			"vehicleOwnership": {
			  "ownerType": "1",
			  "keeperType": "1",
			  "vehicle": {
				"dateOfFirstRegistration": "2017-01-01",
				"dateOfPurchase": "2020-03-25",
				"engineCapacity": 1368,
				"externalAgencyData": true,
				"fuelType": "P",
				"hasTrackingDevice": false,
				"isImported": false,
				"isLeftHandDrive": false,
				"make": "fiat",
				"model": "233 ",
				"registration": "YO66 AAA",
				"seats": 4,
				"securityDeviceType": "g_MAN",
				"transmissionType": "M",
				"vehicleCode": "39082601",
				"yearOfManufacture": 2017,
				"vehicleReference": "VEH123456"
			  }
			},
			"vehicleValue": 1000000,
			"mainDriver": {
			  "vehicleUseType": "g_7",
			  "driver": {
				"person": {
				  "dateOfBirth": "1959-03-11",
				  "dateOfResidency": "1959-03-11",
				  "firstNames": "John",
				  "gender": "M",
				  "isHomeOwner": false,
				  "isUKResidentFromBirth": true,
				  "lastName": "Jackson",
				  "maritalStatus": "M",
				  "nationality": "U",
				  "numberOfDependentChildren": 0,
				  "title": "003",
				  "isDeceased": false,
				  "personReference": "PER123456"
				},
				"licenceType": "F",
				"licenceNumber": "WRIGH855017CC956",
				"dateLicenceObtained": "1999-01-01",
				"monthsLicenceHeld": "8",
				"employments": [
				  {
					"businessType": "431",
					"occupation": "D93",
					"isFullTime": true,
					"isMainEmployment": true,
					"employmentStatusType": "E"
				  }
				],
				"medicalConditionType": "No",
				"hasNonMotorConvictions": false,
				"drivingQualificationsType": "6",
				"dvlaDataIndicator": true,
				"selfDeclaredReason": "006",
				
				"yearsLicenceHeld": "10",
				"driverReference": "DRI123456"
			  },
			  "motorConvictions": [
								  {
									  "convictionCode": "SP30",
									  "convictionDate": "2019-02-21",
									  "endorsementPoints": 3,
									  "disqualificationMonths": 12,
									  "fine": 500,
									  "isConvictionPending": false
								  }
							  ],
							  "incidents": [
								  {
									  "incidentType": "A",
									  "incidentDate": "2019-09-31",
									  "damageType": "A",
									  "incidentValue": 1000,
									  "hasClaimed": true,
									  "faultType": "g_N",
									  "affectedNCD": false,
									  "hasInjuries": false,
									  "claimStatus": "Complete"
								  }
							  ],
			  "numberOfOtherVehicles": 2,
			  "ncd": {
				"yearsNcd": "10",
				"yearsNcdType": "9",
				"namedDriverExperienceType": "Insured",
				"namedDriverNcdYears": "4",
				"isProtected": true,
				"otherVehicleNcdYears": "2",
				"validationStatus": "VAL"
			  },
			  "relationshipToProposerType": "S"
			},
			"annualBusinessMileage": 12000,
			"annualPrivateMileage": 5000,
			"postcodeKeptAt": "HX35AX",
			"nighttimeNotInUseLocationType": "1",
			"daytimeNotInUseLocationType": "1"
		  },
		  "modifications": [
			{
			  "category": "VehModAccessories",
			  "modifiedType": "78"
			}
		  ],
		  "coverStartDateTime": "2021-05-29T20:59:59.000Z",
		  "coverEndDateTime": "2021-03-26T15:59:59.000Z",
		  "hasAdversePolicyAction": false,
		  "inceptionDateTime": "2018-12-30T15:59:59.000Z",
		  "coverType": "01"
		}
	  ],
	  "features": [
		{
		  "insurerID": "COV001",
		  "isSelected": true,
		  "featureType": "1",
		  "code": "AD1",
		  "value": 30,
		  "description": "description",
		  "longDescription": "longDdescription",
		  "excessType": "1",
		  "effectiveDate": "2023-04-27",
		  "endDate": "2021-03-26",
		  "name": "name",
		  "extensionValue": "extensionValue",
		  "valueType": "valueType"
		}
	  ],
	  "fees": [
		{
		  "feeType": "Admin",
		  "value": 100
		}
	  ],
	  "policyStatus": "L",
	  "businessProcess": "NB",
	  "cancellationType": "g_TP",
	  "cancellationReason": "g_SV",
	  "adjustmentReason": "Adjustment",
	  "isAutoRenewal": false,
	  "policyTransactionDate": "2019-10-01T00:00:00.000Z",
	  "propensityScores": {
		"scoreType": "scoreType",
		"value": "value"
	  },
	  "policyDetailsReference": "PDREF36457845",
	  "tenant": {
		"brandId": "BRJL"
	  },
	  "quoteControl": {
		"transmissionDateTime": "2019-11-15T12:37:34.150Z",
		"system": {
		  "schemeIdentifier": "81",
		  "brokerNumber": "63572"
		},
		"document": {
		  "transactionType": "NB",
		  "policyClassType": "1234"
		}
	  }
	},
	"quoteReference": "0a97a99b-bbda-41bc-a7d1-e1cc7687940f"
}